{
  "url": "https://www.ftd.com/",
  "requestedUrl": "https://www.ftd.com/",
  "timestamp": 1717409984594,
  "ranks": {
    "hundos": 1,
    "performance": 1,
    "accessibility": 1,
    "cumulative": 1
  },
  "lighthouse": {
    "version": "11.7.1",
    "performance": 0.52,
    "accessibility": 1,
    "bestPractices": 0.52,
    "seo": 0.91,
    "total": 295
  },
  "firstContentfulPaint": 1975.1127000000004,
  "firstMeaningfulPaint": 1975.1127000000004,
  "speedIndex": 10266.357381771202,
  "largestContentfulPaint": 3345.8048500000004,
  "totalBlockingTime": 3335.3028000000013,
  "cumulativeLayoutShift": 0.0009712885500337727,
  "timeToInteractive": 26238.632400000002,
  "maxPotentialFirstInputDelay": 1112,
  "timeToFirstByte": 774.277,
  "weight": {
    "summary": "183 requests • 2.7 MiB",
    "total": 2825719,
    "image": 499165,
    "imageCount": 44,
    "script": 1646973,
    "scriptCount": 72,
    "document": 82895,
    "font": 293506,
    "fontCount": 6,
    "stylesheet": 39926,
    "stylesheetCount": 7,
    "thirdParty": 1832534,
    "thirdPartyCount": 24
  },
  "run": {
    "number": 3,
    "total": 3
  },
  "sidequests": {
    "-weight.total": 1,
    "+weight.total": 2,
    "-weight.document": 2,
    "+weight.document": 1,
    "-weight.script": 1,
    "+weight.script": 2,
    "-weight.image": 2,
    "+weight.image": 1,
    "-weight.font": 1,
    "+weight.font": 2,
    "+weight.fontCount": 2,
    "-timeToFirstByte": 1,
    "-totalBlockingTime": 1,
    "-largestContentfulPaint": 1
  },
  "axe": {
    "passes": 1952,
    "violations": 11
  }
}